.appveyor.yml
.bumpversion.cfg
.cookiecutterrc
.coveragerc
.editorconfig
.pre-commit-config.yaml
.readthedocs.yml
.travis.yml
AUTHORS.rst
CHANGELOG.rst
CONTRIBUTING.rst
LICENSE
MANIFEST.in
README.rst
setup.cfg
setup.py
tox.ini
ci/appveyor-with-compiler.cmd
ci/bootstrap.py
ci/requirements.txt
ci/templates/.appveyor.yml
ci/templates/.travis.yml
ci/templates/tox.ini
docs/authors.rst
docs/changelog.rst
docs/conf.py
docs/contributing.rst
docs/index.rst
docs/installation.rst
docs/readme.rst
docs/requirements.txt
docs/spelling_wordlist.txt
docs/usage.rst
docs/reference/index.rst
docs/reference/sonicvision.rst
src/sonicvision/__init__.py
src/sonicvision/__main__.py
src/sonicvision/_sonicvision.c
src/sonicvision/cli.py
src/sonicvision.egg-info/PKG-INFO
src/sonicvision.egg-info/SOURCES.txt
src/sonicvision.egg-info/dependency_links.txt
src/sonicvision.egg-info/entry_points.txt
src/sonicvision.egg-info/not-zip-safe
src/sonicvision.egg-info/requires.txt
src/sonicvision.egg-info/top_level.txt
tests/test_sonicvision.py