Metadata-Version: 1.2
Name: sonicvision
Version: 0.0.1
Summary: Quick Prototyping for deep learning based vision tasks
Home-page: https://github.com/sonicvision/sonicvision
Author: Saurav Maheshkar
Author-email: sauravvmaheshkar@gmail.com
License: Apache-2.0
Project-URL: Issue Tracker, https://github.com/sonicvision/sonicvision/issues
Project-URL: Documentation, https://sonicvision.readthedocs.io/
Project-URL: Changelog, https://sonicvision.readthedocs.io/en/latest/changelog.html
Platform: UNKNOWN
Classifier: Development Status :: 1 - Planning
Classifier: Intended Audience :: Developers
Classifier: License :: OSI Approved :: Apache Software License
Classifier: Operating System :: Unix
Classifier: Operating System :: POSIX
Classifier: Operating System :: Microsoft :: Windows
Classifier: Programming Language :: Python
Classifier: Programming Language :: Python :: 2.7
Classifier: Programming Language :: Python :: 3
Classifier: Programming Language :: Python :: 3.5
Classifier: Programming Language :: Python :: 3.6
Classifier: Programming Language :: Python :: 3.7
Classifier: Programming Language :: Python :: 3.8
Classifier: Programming Language :: Python :: 3.9
Classifier: Programming Language :: Python :: Implementation :: CPython
Classifier: Programming Language :: Python :: Implementation :: PyPy
Requires-Python: >=2.7, !=3.0.*, !=3.1.*, !=3.2.*, !=3.3.*, !=3.4.*
